airtag_bat/__init__.py
airtag_bat/main.py
airtag_bat-1.0.1.dist-info/LICENSE
airtag_bat-1.0.1.dist-info/METADATA
airtag_bat-1.0.1.dist-info/WHEEL
airtag_bat-1.0.1.dist-info/entry_points.txt
airtag_bat-1.0.1.dist-info/top_level.txt
airtag_bat-1.0.1.dist-info/RECORD
